dfshell-1.2.data/scripts/dfshell
test2/SDomDiscover.py
test2/setup.py
test2/build/lib/SDomDiscover.py
dfshell-1.2.dist-info/METADATA
dfshell-1.2.dist-info/WHEEL
dfshell-1.2.dist-info/top_level.txt
dfshell-1.2.dist-info/RECORD
